seabornxt/__init__.py
seabornxt/_version.py
seabornxt/sboxplot.py
seabornxt-0.0.1.dev15.dist-info/LICENSE
seabornxt-0.0.1.dev15.dist-info/METADATA
seabornxt-0.0.1.dev15.dist-info/WHEEL
seabornxt-0.0.1.dev15.dist-info/top_level.txt
seabornxt-0.0.1.dev15.dist-info/RECORD
