Metadata-Version: 2.1
Name: seabornxt
Version: 0.0.1.dev15
Summary: A few handy extension plots using seaborn API.
Author: Leonard Sasse
Author-email: l.sasse@fz-juelich.de
Project-URL: repository, https://github.com/LeSasse/seabornxt.git
Keywords: plotting
Classifier: Development Status :: 4 - Beta
Classifier: Intended Audience :: Science/Research
Classifier: Intended Audience :: Developers
Classifier: License :: OSI Approved
Classifier: Natural Language :: English
Classifier: Topic :: Software Development
Classifier: Topic :: Scientific/Engineering
Classifier: Topic :: Scientific/Engineering :: Bio-Informatics
Classifier: Operating System :: OS Independent
Classifier: Programming Language :: Python :: 3
Requires-Python: >=3.7
License-File: LICENSE
Requires-Dist: seaborn >=0.12.2
Provides-Extra: dev
Requires-Dist: tox ; extra == 'dev'
